bump_bep621/bump.py
bump_bep621/main.py
bump_pep621-0.0.12.dist-info/METADATA
bump_pep621-0.0.12.dist-info/WHEEL
bump_pep621-0.0.12.dist-info/entry_points.txt
bump_pep621-0.0.12.dist-info/RECORD
